{
    "name": "GMEOW",
    "maxSupply": "1000000000.0",
    "totalSupply": "998405402.35108876",
    "circulatingSupply": "998405402.35108876",
    "szDecimals": 0,
    "weiDecimals": 8,
    "midPx": "0.00060214",
    "markPx": "0.00060124",
    "prevDayPx": "0.00061952",
    "genesis": {
        "userBalances": [
            [
                "0x1c49e03f3683fd39bc01751378c7f59cbb97d1b0",
                "50000000.0"
            ],
            [
                "0xffffffffffffffffffffffffffffffffffffffff",
                "600000000.0"
            ]
        ],
        "existingTokenBalances": [
            [
                1,
                "350000000.0"
            ]
        ]
    },
    "deployer": "0x1c49e03f3683fd39bc01751378c7f59cbb97d1b0",
    "deployGas": "0.0",
    "deployTime": "2024-06-01T11:28:17.383",
    "seededUsdc": "0.0",
    "nonCirculatingUserBalances": [],
    "futureEmissions": "0.0"
}