{
    "name": "SELL",
    "maxSupply": "400000000.0",
    "totalSupply": "393942919.88533002",
    "circulatingSupply": "318969910.30633003",
    "szDecimals": 0,
    "weiDecimals": 5,
    "midPx": "0.00040931",
    "markPx": "0.0004087",
    "prevDayPx": "0.00043005",
    "genesis": {
        "userBalances": [
            [
                "0x03738f950aa079dc8afbe287244111f29e2d3bb5",
                "100000000.0"
            ],
            [
                "0xffffffffffffffffffffffffffffffffffffffff",
                "100000000.0"
            ]
        ],
        "existingTokenBalances": [
            [
                1,
                "100000000.0"
            ],
            [
                5,
                "100000000.0"
            ]
        ]
    },
    "deployer": "0x03738f950aa079dc8afbe287244111f29e2d3bb5",
    "deployGas": "6858.542719",
    "deployTime": "2024-06-26T06:10:57.298",
    "seededUsdc": "0.0",
    "nonCirculatingUserBalances": [
        [
            "0x0000000000000000000000000000000000000000",
            "87946.0"
        ],
        [
            "0x000000000000000000000000000000000000dead",
            "74885063.579"
        ]
    ],
    "futureEmissions": "0.0"
}